AUTHORS
LICENSE
MANIFEST.in
README.rst
setup.py
cmsplugin_events/__init__.py
cmsplugin_events/admin.py
cmsplugin_events/cms_app.py
cmsplugin_events/cms_plugins.py
cmsplugin_events/models.py
cmsplugin_events/urls.py
cmsplugin_events/views.py
cmsplugin_events/migrations/0001_initial.py
cmsplugin_events/migrations/0002_auto__add_field_event_facebook_url.py
cmsplugin_events/migrations/__init__.py
cmsplugin_events/tests/__init__.py
django_cms_events.egg-info/PKG-INFO
django_cms_events.egg-info/SOURCES.txt
django_cms_events.egg-info/dependency_links.txt
django_cms_events.egg-info/not-zip-safe
django_cms_events.egg-info/requires.txt
django_cms_events.egg-info/top_level.txt